pytest_cobra/__init__.py
pytest_cobra-1.0.4.dist-info/LICENSE
pytest_cobra-1.0.4.dist-info/METADATA
pytest_cobra-1.0.4.dist-info/WHEEL
pytest_cobra-1.0.4.dist-info/entry_points.txt
pytest_cobra-1.0.4.dist-info/top_level.txt
pytest_cobra-1.0.4.dist-info/RECORD
