Metadata-Version: 2.1
Name: pytest-cobra
Version: 1.0.4
Summary: PyTest plugin for testing Smart Contracts for Ethereum blockchain.
Home-page: https://github.com/cobraframework/pytest-cobra
Author: Meheret Tesfaye
Author-email: meherett@zoho.com
License: MIT
Platform: UNKNOWN
Classifier: Development Status :: 3 - Alpha
Classifier: License :: OSI Approved :: MIT License
Classifier: Programming Language :: Python :: 3.6
Classifier: Programming Language :: Python :: 3.7
Classifier: Framework :: Pytest
Requires-Python: >=3.6,<3.8
Requires-Dist: pytest (<4.0.0,>=3.7.1)
Requires-Dist: eth-keyfile (==0.5.1)
Requires-Dist: eth-tester (==0.1.0b33)
Requires-Dist: py-evm (==0.2.0a33)
Requires-Dist: eth-abi (==1.2.2)
Requires-Dist: py-ecc (==1.4.3)
Requires-Dist: py-solc (<4.0.0,>=3.2.0)
Requires-Dist: web3 (<5.0.0,>=4.4.1)
Requires-Dist: PyYAML (<4.0,>=3.13)
